pika_id/__init__.py
pika_id/pika.py
pika_id/snowflake.py
pika_id-0.0.1.dist-info/LICENSE
pika_id-0.0.1.dist-info/WHEEL
pika_id-0.0.1.dist-info/METADATA
pika_id-0.0.1.dist-info/RECORD
